odoo/addons/l10n_it_causali_pagamento/README.rst
odoo/addons/l10n_it_causali_pagamento/__init__.py
odoo/addons/l10n_it_causali_pagamento/__manifest__.py
odoo/addons/l10n_it_causali_pagamento/data/causali_pagamento_data.xml
odoo/addons/l10n_it_causali_pagamento/i18n/it.po
odoo/addons/l10n_it_causali_pagamento/i18n/l10n_it_causali_pagamento.pot
odoo/addons/l10n_it_causali_pagamento/migrations/12.0.1.1.0/post-migrate.py
odoo/addons/l10n_it_causali_pagamento/models/__init__.py
odoo/addons/l10n_it_causali_pagamento/models/causale_pagamento.py
odoo/addons/l10n_it_causali_pagamento/readme/CONFIGURE.rst
odoo/addons/l10n_it_causali_pagamento/readme/CONTRIBUTORS.rst
odoo/addons/l10n_it_causali_pagamento/readme/DESCRIPTION.rst
odoo/addons/l10n_it_causali_pagamento/readme/USAGE.rst
odoo/addons/l10n_it_causali_pagamento/security/ir.model.access.csv
odoo/addons/l10n_it_causali_pagamento/static/description/icon.png
odoo/addons/l10n_it_causali_pagamento/static/description/index.html
odoo/addons/l10n_it_causali_pagamento/tests/__init__.py
odoo/addons/l10n_it_causali_pagamento/tests/test_causali.py
odoo/addons/l10n_it_causali_pagamento/views/causali_pagamento_view.xml
odoo12_addon_l10n_it_causali_pagamento-12.0.2.0.0.dist-info/METADATA
odoo12_addon_l10n_it_causali_pagamento-12.0.2.0.0.dist-info/WHEEL
odoo12_addon_l10n_it_causali_pagamento-12.0.2.0.0.dist-info/top_level.txt
odoo12_addon_l10n_it_causali_pagamento-12.0.2.0.0.dist-info/RECORD
