Metadata-Version: 2.1
Name: odoo12-addon-l10n-it-causali-pagamento
Version: 12.0.2.0.0
Summary: Aggiunge la tabella delle causali di pagamento da usare ad esempio nelle ritenute d'acconto
Home-page: https://github.com/OCA/l10n-italy/
Author: Agile Business Group,Odoo Community Association (OCA)
Author-email: support@odoo-community.org
License: AGPL-3
Platform: UNKNOWN
Classifier: Programming Language :: Python
Classifier: Framework :: Odoo
Classifier: License :: OSI Approved :: GNU Affero General Public License v3
Classifier: Development Status :: 5 - Production/Stable
Requires-Python: >=3.5
Requires-Dist: odoo12-addon-l10n-it-account
Requires-Dist: odoo (<12.1dev,>=12.0a)
